ms9/__init__.py
ms9/main.cp313-win_amd64.pyd
ms9-0.14.7.dist-info/METADATA
ms9-0.14.7.dist-info/WHEEL
ms9-0.14.7.dist-info/top_level.txt
ms9-0.14.7.dist-info/RECORD
